articolare/__init__.py
articolare/translate.py
tests/__init__.py
tests/test_client.py
articolare-1.1.2.dist-info/METADATA
articolare-1.1.2.dist-info/WHEEL
articolare-1.1.2.dist-info/top_level.txt
articolare-1.1.2.dist-info/RECORD
