Metadata-Version: 2.1
Name: articolare
Version: 1.1.2
Summary: Python client for the Articolare API
Author: Murilo Silvestre
Classifier: Development Status :: 3 - Alpha
Classifier: Intended Audience :: Developers
Classifier: License :: OSI Approved :: MIT License
Classifier: Programming Language :: Python :: 3
Classifier: Programming Language :: Python :: 3.6
Classifier: Programming Language :: Python :: 3.7
Classifier: Programming Language :: Python :: 3.8
Classifier: Programming Language :: Python :: 3.9
Classifier: Programming Language :: Python :: 3.10
Requires-Python: >=3.6
Requires-Dist: requests
Requires-Dist: certifi (==2023.5.7)
Requires-Dist: charset-normalizer (==3.1.0)
Requires-Dist: exceptiongroup (==1.1.1)
Requires-Dist: idna (==3.4)
Requires-Dist: iniconfig (==2.0.0)
Requires-Dist: packaging (==23.1)
Requires-Dist: pluggy (==1.0.0)
Requires-Dist: requests (==2.31.0)
Requires-Dist: tomli (==2.0.1)
Requires-Dist: urllib3 (==2.0.3)
Provides-Extra: dev
Requires-Dist: pytest (>=3.7) ; extra == 'dev'
